helloworld_proto/__init__.py
helloworld_proto/helloworld/__init__.py
helloworld_proto/helloworld/v1/__init__.py
helloworld_proto/helloworld/v1/helloworld_pb2.py
helloworld_proto/helloworld/v1/helloworld_pb2.pyi
helloworld_proto/helloworld/v1/helloworld_pb2_grpc.py
helloworld_proto/helloworld/v1/helloworld_pb2_grpc.pyi
helloworld_proto-1.0.0.dist-info/METADATA
helloworld_proto-1.0.0.dist-info/WHEEL
helloworld_proto-1.0.0.dist-info/top_level.txt
helloworld_proto-1.0.0.dist-info/RECORD
