Metadata-Version: 2.1
Name: helloworld-proto
Version: 1.0.0
Summary: Proto example package
Home-page: https://github.com/RefaceAI/helloworld-proto
Author: Reface
Classifier: Programming Language :: Python
Classifier: Programming Language :: Python :: 3
Classifier: Programming Language :: Python :: 3.8
Classifier: Programming Language :: Python :: 3.9
Classifier: Programming Language :: Python :: 3.10
Classifier: Programming Language :: Python :: 3.11
Classifier: Programming Language :: Python :: 3.12
Classifier: Programming Language :: Python :: 3.13
Requires-Dist: googleapis-common-protos>=1.52.0
